hyperflask_deploy/__init__.py
hyperflask_deploy/playbooks/setup.yml
hyperflask_deploy-0.1.0.dist-info/METADATA
hyperflask_deploy-0.1.0.dist-info/WHEEL
hyperflask_deploy-0.1.0.dist-info/entry_points.txt
hyperflask_deploy-0.1.0.dist-info/RECORD
