Metadata-Version: 2.1
Name: hyperflask-deploy
Version: 0.1.0
Summary: Deployment support for Hyperflask
Home-page: https://github.com/hyperflask/hyperflask-deploy
License: MIT
Author: Maxime Bouroumeau-Fuseau
Author-email: maxime.bouroumeau@gmail.com
Requires-Python: >=3.10,<4.0
Classifier: License :: OSI Approved :: MIT License
Classifier: Programming Language :: Python :: 3
Classifier: Programming Language :: Python :: 3.10
Classifier: Programming Language :: Python :: 3.11
Classifier: Programming Language :: Python :: 3.12
Requires-Dist: flask (>=3.0,<4.0)
Project-URL: Repository, https://github.com/hyperflask/hyperflask-deploy
